tests/__init__.py
virva/__init__.py
virva/cities.py
virva/core.py
virva/countries.py
virva/diseases.py
virva/foods.py
virva/jobs.py
virva/names.py
virva/us_state.py
virva-0.1.9.dist-info/LICENSE.txt
virva-0.1.9.dist-info/METADATA
virva-0.1.9.dist-info/WHEEL
virva-0.1.9.dist-info/top_level.txt
virva-0.1.9.dist-info/RECORD
