Metadata-Version: 2.1
Name: virva
Version: 0.1.9
Summary: Virva is the simplest  fake dataframe generator 
Home-page: https://github.com/charleslf2/virva
Author: Charles TCHANAKE
Author-email: datadevfernolf@gmail.com
License: MIT
Project-URL: Bug Tracker, https://github.com/charleslf2/virva/issues
Keywords: data generator,fake data generator,csv generator,dataframe generator
Classifier: License :: OSI Approved :: MIT License
Classifier: Programming Language :: Python :: 3
Classifier: Operating System :: OS Independent
Classifier: Development Status :: 4 - Beta
License-File: LICENSE.txt
Requires-Dist: pandas
Requires-Dist: rich
